fandak/__init__.py
fandak/core/__init__.py
fandak/core/datasets.py
fandak/core/evaluators.py
fandak/core/models.py
fandak/core/trainers.py
fandak/utils/__init__.py
fandak/utils/click.py
fandak/utils/config.py
fandak/utils/data_parallel.py
fandak/utils/locks.py
fandak/utils/metrics.py
fandak/utils/misc.py
fandak/utils/torch.py
fandak-0.1.3.1.dist-info/LICENSE
fandak-0.1.3.1.dist-info/METADATA
fandak-0.1.3.1.dist-info/WHEEL
fandak-0.1.3.1.dist-info/top_level.txt
fandak-0.1.3.1.dist-info/RECORD
