Metadata-Version: 2.1
Name: fandak
Version: 0.1.3.1
Summary: A Framework for ML Research Using PyTorch
Home-page: https://github.com/yassersouri/fandak
Author: Yasser Souri
Author-email: yassersouri@gmail.com
License: UNKNOWN
Platform: UNKNOWN
Classifier: Programming Language :: Python :: 3.7
Classifier: License :: OSI Approved :: MIT License
Classifier: Operating System :: OS Independent
Classifier: Development Status :: 2 - Pre-Alpha
Classifier: Intended Audience :: Science/Research
Classifier: Topic :: Scientific/Engineering :: Artificial Intelligence
Classifier: Topic :: Scientific/Engineering :: Image Recognition
Classifier: Typing :: Typed
Requires-Dist: torch (>=1.1)
Requires-Dist: torchvision (>=0.3)
Requires-Dist: tqdm (>=4.32)
Requires-Dist: matplotlib (>=3.0.0)
Requires-Dist: tensorboard (>=1.14.0)
Requires-Dist: future (>=0.17.1)
Requires-Dist: yacs (>=0.1.6)
Requires-Dist: click (>=7.0)
Requires-Dist: oslo-concurrency (>=4.2.0)
